backbone_learn/__init__.py
backbone_learn/backbone/__init__ .py
backbone_learn/backbone/backbone_base.py
backbone_learn/backbone/backbone_clustering.py
backbone_learn/backbone/backbone_decision_tree.py
backbone_learn/backbone/backbone_sparse_regression.py
backbone_learn/backbone/backbone_supervised.py
backbone_learn/backbone/backbone_unsupervised.py
backbone_learn/backbone/subproblem_costructor.py
backbone_learn/backbone/subproblem_feature_selector.py
backbone_learn/exact_solvers/__init__.py
backbone_learn/exact_solvers/benders_oct_decision_tree.py
backbone_learn/exact_solvers/exact_solver_base.py
backbone_learn/exact_solvers/lobnb_regression.py
backbone_learn/exact_solvers/lobnb_regression_model.py
backbone_learn/exact_solvers/mio_clustering.py
backbone_learn/heuristic_solvers/__init__.py
backbone_learn/heuristic_solvers/cart_decision_tree.py
backbone_learn/heuristic_solvers/heauristic_solver_base.py
backbone_learn/heuristic_solvers/kmeans_solver.py
backbone_learn/heuristic_solvers/lasso_regression.py
backbone_learn/screen_selectors/__init__.py
backbone_learn/screen_selectors/linear_regression_selector.py
backbone_learn/screen_selectors/pearson_correlation_selector.py
backbone_learn/screen_selectors/screen_selector_base.py
backbone_learn/screen_selectors/variable_selector.py
backbone_learn/utils/__init__ .py
backbone_learn/utils/utils.py
backbone_learn-0.1.3.dist-info/LICENSE
backbone_learn-0.1.3.dist-info/METADATA
backbone_learn-0.1.3.dist-info/WHEEL
backbone_learn-0.1.3.dist-info/RECORD
