Metadata-Version: 2.1
Name: backbone-learn
Version: 0.1.3
Summary: A Library for Scaling Mixed-Integer Optimization-Based Machine Learning.
Author: Christos Ziakas, Vassilis Digalakis Jr.
Requires-Python: >=3.9,<3.12
Classifier: Programming Language :: Python :: 3
Classifier: Programming Language :: Python :: 3.9
Classifier: Programming Language :: Python :: 3.10
Classifier: Programming Language :: Python :: 3.11
Requires-Dist: ipykernel (>=6.26.0,<7.0.0)
Requires-Dist: jupyter (>=1.0.0,<2.0.0)
Requires-Dist: l0bnb (>=1.0.0,<2.0.0)
Requires-Dist: numpy (>=1.26.1,<2.0.0)
Requires-Dist: pre-commit (>=3.5.0,<4.0.0)
Requires-Dist: pulp (>=2.7.0,<3.0.0)
Requires-Dist: pytest (>=7.4.3,<8.0.0)
Requires-Dist: scikit-learn (>=1.3.2,<2.0.0)
Requires-Dist: seaborn (>=0.13.0,<0.14.0)
